readme2tex/__init__.py
readme2tex/__main__.py
readme2tex/render.py
readme2tex-0.0.1b2.dist-info/DESCRIPTION.rst
readme2tex-0.0.1b2.dist-info/LICENSE.txt
readme2tex-0.0.1b2.dist-info/METADATA
readme2tex-0.0.1b2.dist-info/RECORD
readme2tex-0.0.1b2.dist-info/WHEEL
readme2tex-0.0.1b2.dist-info/metadata.json
readme2tex-0.0.1b2.dist-info/top_level.txt
