Metadata-Version: 2.0
Name: readme2tex
Version: 0.0.1b2
Summary: Render LaTeX within your Github Readmes
Home-page: http://github.com/leegao/readme2tex
Author: Lee Gao
Author-email: lg342@cornell.edu
License: MIT
Keywords: github readme markdown latex tex equations math svg markup
Platform: UNKNOWN
Classifier: Development Status :: 3 - Alpha
Classifier: License :: OSI Approved :: MIT License
Classifier: Programming Language :: Python :: 2.7
Classifier: Topic :: Text Processing :: Markup :: LaTeX
Requires-Dist: markdown
Requires-Dist: pygments
